{"cameraMode":{"drawMode":0,"name":"Shaded","section":"Shading Mode"},"sceneLighting":true,"audioPlay":false,"sceneViewState":{"showFog":true,"showMaterialUpdate":false,"showSkybox":true,"showFlares":true,"showImageEffects":true,"showParticleSystems":true},"in2DMode":false,"pivot":{"x":13.973600387573243,"y":17.466285705566408,"z":-170.54608154296876},"rotation":{"x":-0.05259406566619873,"y":0.9048339128494263,"z":-0.40593260526657107,"w":-0.11722908169031143},"size":44.68326187133789,"orthographic":false}